inscodeai/__init__.py
inscodeai/inscodeai.py
inscodeai-0.2.0.dist-info/METADATA
inscodeai-0.2.0.dist-info/WHEEL
inscodeai-0.2.0.dist-info/top_level.txt
inscodeai-0.2.0.dist-info/RECORD
